epsteinsovereigncitizens/__init__.py
epsteinsovereigncitizens/agents.py
epsteinsovereigncitizens/model.py
epsteinsovereigncitizens-1.0.1.dist-info/METADATA
epsteinsovereigncitizens-1.0.1.dist-info/WHEEL
epsteinsovereigncitizens-1.0.1.dist-info/licenses/LICENSE
epsteinsovereigncitizens-1.0.1.dist-info/RECORD
